{"version":3,"kind":"Article","sha256":"2786b3551bce9ba7d415881ddcc3fe6ae93e0398b9d74e808b620b94637e5311","slug":"index","location":"/inicio.md","dependencies":[],"frontmatter":{"title":"Inicio","content_includes_title":false,"authors":[{"nameParsed":{"literal":"Victor Muntean Erhan","given":"Victor Muntean","family":"Erhan"},"name":"Victor Muntean Erhan","id":"contributors-myst-generated-uid-0"}],"license":{"content":{"id":"CC-BY-4.0","url":"https://creativecommons.org/licenses/by/4.0/","name":"Creative Commons Attribution 4.0 International","free":true,"CC":true}},"exports":[{"format":"md","filename":"inicio.md","url":"/Apuntes/build/inicio-d6a928270e29218b6885f98ff46b2dcc.md"}]},"mdast":{"type":"root","children":[{"type":"block","children":[{"type":"heading","depth":2,"position":{"start":{"line":3,"column":1},"end":{"line":3,"column":1}},"children":[{"type":"text","value":"Proyecto blah blah blah.","position":{"start":{"line":3,"column":1},"end":{"line":3,"column":1}},"key":"fQqik20NXS"}],"identifier":"proyecto-blah-blah-blah","label":"Proyecto blah blah blah.","html_id":"proyecto-blah-blah-blah","implicit":true,"key":"jWv8gnr0k0"},{"type":"paragraph","position":{"start":{"line":5,"column":1},"end":{"line":5,"column":1}},"children":[{"type":"text","value":"El proyecto en el que nos hemos embarcado entraña un complejidad importate debido a la necesidad de compaginar el funcionamiento de diferentes equipos y subsistemas para conseguir resultados adecuados. Para ellos se intenta estructurar en este manual el contenido necesario para un seguimiento rápido de los distintos pasos a seguir así como para una mejor organización de la amplia documentación que se debe consultar.","position":{"start":{"line":5,"column":1},"end":{"line":5,"column":1}},"key":"BEY8GFuhtm"}],"key":"gvQ4i43slD"},{"type":"paragraph","position":{"start":{"line":7,"column":1},"end":{"line":10,"column":1}},"children":[{"type":"text","value":"This is a small sample book to give you a feel for how book content is\nstructured.\nIt shows off a few of the major file types, as well as some sample content.\nIt does not go in-depth into any particular topic - check out ","position":{"start":{"line":7,"column":1},"end":{"line":7,"column":1}},"key":"lnGwXXwBE6"},{"type":"link","url":"https://jupyterbook.org","position":{"start":{"line":7,"column":1},"end":{"line":7,"column":1}},"children":[{"type":"text","value":"the Jupyter Book documentation","position":{"start":{"line":7,"column":1},"end":{"line":7,"column":1}},"key":"RE2L7qXiUl"}],"urlSource":"https://jupyterbook.org","key":"m96ksChMiF"},{"type":"text","value":" for more information.","position":{"start":{"line":7,"column":1},"end":{"line":7,"column":1}},"key":"sNOzpCQvEt"}],"key":"BQWmd3fvwo"},{"type":"paragraph","position":{"start":{"line":12,"column":1},"end":{"line":12,"column":1}},"children":[{"type":"text","value":"Check out the content pages bundled with this sample book to see more.","position":{"start":{"line":12,"column":1},"end":{"line":12,"column":1}},"key":"hMD3PVHbOC"}],"key":"qouqiVzvE9"},{"type":"block","children":[{"type":"list","children":[{"type":"listItem","children":[{"type":"link","url":"/","internal":true,"children":[{"type":"text","value":"Apuntes de mecánica de fluidos","key":"Y0DU8DHjpP"}],"urlSource":"/","key":"HcP0Xt3nS2"}],"key":"qHpA8FHtjO"},{"type":"listItem","children":[{"type":"text","value":"Mecánica de Fluidos","key":"v703szms1l"},{"type":"list","children":[{"type":"listItem","children":[{"type":"link","url":"/intro","internal":true,"children":[{"type":"text","value":"Introducción","key":"pevfjEgNir"}],"urlSource":"/intro","dataUrl":"/intro.json","protocol":"file","key":"Q1tEL0SPwO"}],"key":"dqVxLoE3EC"},{"type":"listItem","children":[{"type":"link","url":"/cinematica","internal":true,"children":[{"type":"text","value":"Cinemática","key":"CJcwCIDed3"}],"urlSource":"/cinematica","dataUrl":"/cinematica.json","protocol":"file","key":"nkucDPpQUl"}],"key":"LhEhFW6lab"}],"key":"atxl96AWjg"}],"key":"GkHxAEHJTC"}],"key":"tzp3jN3muf"}],"data":{"part":"toc:project"},"key":"UXlhP7hPT2"}],"key":"i7LmiopEr1"}],"key":"KU0cWdn5kx"},"references":{"cite":{"order":[],"data":{}}},"footer":{"navigation":{"next":{"title":"Introducción","url":"/intro","group":"Mecánica de Fluidos"}}},"domain":"http://localhost:3000"}