{"version":3,"kind":"Article","sha256":"a6ca4ee3027d32f42b092a1a12cc1ea7c0f8af1f39d1b0938137b47a52b2e1bb","slug":"prefacio","location":"/prefacio.md","dependencies":[],"frontmatter":{"title":"Prefacio","authors":[{"nameParsed":{"literal":"Victor Muntean Erhan","given":"Victor Muntean","family":"Erhan"},"name":"Victor Muntean Erhan","id":"contributors-myst-generated-uid-0"}],"license":{"content":{"id":"CC-BY-4.0","url":"https://creativecommons.org/licenses/by/4.0/","name":"Creative Commons Attribution 4.0 International","free":true,"CC":true}},"exports":[{"format":"md","filename":"prefacio.md","url":"/Apuntes/build/prefacio-f38251ba7e4fc915a5093d6ce154a7e0.md"}]},"mdast":{"type":"root","children":[{"type":"block","children":[{"type":"paragraph","position":{"start":{"line":5,"column":1},"end":{"line":5,"column":1}},"children":[{"type":"text","value":"El proyecto en el que nos hemos embarcado entraña un complejidad importate debido a la necesidad de compaginar el funcionamiento de diferentes equipos y subsistemas para conseguir resultados adecuados. Para ellos se intenta estructurar en este manual el contenido necesario para un seguimiento rápido de los distintos pasos a seguir así como para una mejor organización de la amplia documentación que se debe consultar.","position":{"start":{"line":5,"column":1},"end":{"line":5,"column":1}},"key":"tlKgIgYArv"}],"key":"LoABGeH9sr"},{"type":"paragraph","position":{"start":{"line":7,"column":1},"end":{"line":10,"column":1}},"children":[{"type":"text","value":"This is a small sample book to give you a feel for how book content is\nstructured.\nIt shows off a few of the major file types, as well as some sample content.\nIt does not go in-depth into any particular topic - check out ","position":{"start":{"line":7,"column":1},"end":{"line":7,"column":1}},"key":"AwLNVbdDMY"},{"type":"link","url":"https://jupyterbook.org","position":{"start":{"line":7,"column":1},"end":{"line":7,"column":1}},"children":[{"type":"text","value":"the Jupyter Book documentation","position":{"start":{"line":7,"column":1},"end":{"line":7,"column":1}},"key":"NrWAm2hSnJ"}],"urlSource":"https://jupyterbook.org","key":"XLwFmnOswZ"},{"type":"text","value":" for more information.","position":{"start":{"line":7,"column":1},"end":{"line":7,"column":1}},"key":"BaP0GMjSb1"}],"key":"EFm3vUD8ER"},{"type":"paragraph","position":{"start":{"line":12,"column":1},"end":{"line":12,"column":1}},"children":[{"type":"text","value":"Check out the content pages bundled with this sample book to see more.","position":{"start":{"line":12,"column":1},"end":{"line":12,"column":1}},"key":"vJmlmDC15O"}],"key":"v3UdLLNZPR"}],"key":"KpjgJBF5Rn"}],"key":"d8oPZWDwBs"},"references":{"cite":{"order":[],"data":{}}},"footer":{"navigation":{"prev":{"title":"Apuntes de mecánica de fluidos","url":"/","group":"Apuntes de mecánica de fluidos"},"next":{"title":"Introducción","url":"/intro","group":"Apuntes de mecánica de fluidos"}}},"domain":"http://localhost:3000"}